accelrod/__init__.py
accelrod/benchmark.py
accelrod/device.py
accelrod/utils.py
accelrod-0.1.0.dist-info/LICENSE
accelrod-0.1.0.dist-info/METADATA
accelrod-0.1.0.dist-info/WHEEL
accelrod-0.1.0.dist-info/top_level.txt
accelrod-0.1.0.dist-info/RECORD
