Metadata-Version: 2.2
Name: accelrod
Version: 0.1.0
Summary: A library for benchmarking the tflops of accelerators
Classifier: Programming Language :: Python :: 3 :: Only
Classifier: Programming Language :: Python :: 3.10
Classifier: Programming Language :: Python :: 3.11
Classifier: Programming Language :: Python :: 3.12
Classifier: Programming Language :: Python :: 3.13
Requires-Python: >=3.10
License-File: LICENSE
Requires-Dist: matplotlib>=3.10.0
Requires-Dist: pandas>=2.2.3
Requires-Dist: plotly>=6.0.0
Requires-Dist: torch>=2.5.1
Requires-Dist: torchvision>=0.20.1
